easy_vic_build/Evb_dir_class.py
easy_vic_build/Logger.py
easy_vic_build/__init__.py
easy_vic_build/build_GlobalParam.py
easy_vic_build/build_MeteForcing.py
easy_vic_build/build_Param.py
easy_vic_build/build_RVIC_Param.py
easy_vic_build/build_hydroanalysis.py
easy_vic_build/bulid_Domain.py
easy_vic_build/calibrate.py
easy_vic_build/warmup.py
easy_vic_build/backup/build_MeteForcing.py
easy_vic_build/backup/build_MeteForcing_nco.py
easy_vic_build/backup/build_dpc.py
easy_vic_build/backup/test_build_MeteForcing_nco.py
easy_vic_build/data/NLDAS_Veg_monthly.xlsx
easy_vic_build/data/NLDAS_annual_prec.npy
easy_vic_build/data/NLDAS_annual_prec.tiff
easy_vic_build/data/annual_prec_lat.txt
easy_vic_build/data/annual_prec_lon.txt
easy_vic_build/data/global_param_reference.txt
easy_vic_build/data/rvic.convolution.reference.cfg
easy_vic_build/data/rvic.parameters.reference.cfg
easy_vic_build/data/veg_type_attributes_umd.json
easy_vic_build/data/veg_type_attributes_umd_updated.json
easy_vic_build/tools/__init__.py
easy_vic_build/tools/decoractors.py
easy_vic_build/tools/utilities.py
easy_vic_build/tools/calibrate_func/__init__.py
easy_vic_build/tools/calibrate_func/algorithm_NSGAII.py
easy_vic_build/tools/calibrate_func/evaluate_metrics.py
easy_vic_build/tools/calibrate_func/sampling.py
easy_vic_build/tools/dpc_func/__init__.py
easy_vic_build/tools/dpc_func/aggregate.py
easy_vic_build/tools/dpc_func/basin_grid_class.py
easy_vic_build/tools/dpc_func/basin_grid_func.py
easy_vic_build/tools/dpc_func/dpc_base.py
easy_vic_build/tools/dpc_func/dpc_subclass.py
easy_vic_build/tools/dpc_func/select_basin_shp.py
easy_vic_build/tools/dpc_func/backup/dpc_subclass.py
easy_vic_build/tools/dpc_func/backup/readdataIntoBasins_interface.py
easy_vic_build/tools/dpc_func/backup/readdataIntoGrids_interface.py
easy_vic_build/tools/dpc_func/extractData_func/Extract_CAMELS_Attribute.py
easy_vic_build/tools/dpc_func/extractData_func/Extract_CAMELS_ForcingDaymet.py
easy_vic_build-0.1.0.dist-info/licenses/LICENSE
easy_vic_build-0.1.0.dist-info/METADATA
easy_vic_build-0.1.0.dist-info/WHEEL
easy_vic_build-0.1.0.dist-info/top_level.txt
easy_vic_build-0.1.0.dist-info/RECORD
