Metadata-Version: 2.4
Name: easy_vic_build
Version: 0.1.0
Summary: An open-source Python package for VIC model deployment.
Author-email: XudongZheng <zhengxd@sehemodel.club>
License: MIT License
Project-URL: Homepage, https://github.com/XudongZhengSteven/easy_vic_build
Project-URL: Repository, https://github.com/XudongZhengSteven/easy_vic_build
Classifier: Programming Language :: Python :: 3
Classifier: License :: OSI Approved :: MIT License
Classifier: Operating System :: OS Independent
Requires-Python: >=3.9
License-File: LICENSE
Requires-Dist: numpy>=1.21.2
Requires-Dist: pandas>=1.4.3
Requires-Dist: matplotlib>=3.9.2
Requires-Dist: scipy>=1.13.1
Requires-Dist: tqdm>=4.66.5
Requires-Dist: eofs>=2.0.0
Requires-Dist: geopandas>=0.10.1
Requires-Dist: netcdf4>=1.7.1
Requires-Dist: cfgrib>=0.9.10.3
Requires-Dist: xarray>=2023.8.0
Requires-Dist: rasterio>=1.4.1
Requires-Dist: cartopy>=0.23.0
Requires-Dist: shapely>=2.0.6
Requires-Dist: cdo>=1.6.1
Requires-Dist: whitebox-workflows>=1.3.3
Requires-Dist: deap>=1.4.1
Provides-Extra: dev
Requires-Dist: pytest>=6.0; extra == "dev"
Requires-Dist: black>=21.0; extra == "dev"
Provides-Extra: nco
Requires-Dist: nco>=1.1.2; extra == "nco"
Provides-Extra: rvic
Requires-Dist: rvic>=1.1.1; extra == "rvic"
Provides-Extra: nco-rvic
Requires-Dist: nco>=1.1.2; extra == "nco-rvic"
Requires-Dist: rvic>=1.1.1; extra == "nco-rvic"
Dynamic: license-file
